jsondb/compat.py
jsondb/file_writer.py
jsondb/__init__.py
jsondb/db.py
jsondatabase-0.1.7.dist-info/RECORD
jsondatabase-0.1.7.dist-info/top_level.txt
jsondatabase-0.1.7.dist-info/metadata.json
jsondatabase-0.1.7.dist-info/zip-safe
jsondatabase-0.1.7.dist-info/METADATA
jsondatabase-0.1.7.dist-info/DESCRIPTION.rst
jsondatabase-0.1.7.dist-info/WHEEL
