Metadata-Version: 1.1
Name: jsondatabase
Version: 0.1.7
Summary: 
